Flask_Sendwithus-1.0.2.dist-info/DESCRIPTION.rst
Flask_Sendwithus-1.0.2.dist-info/METADATA
Flask_Sendwithus-1.0.2.dist-info/RECORD
Flask_Sendwithus-1.0.2.dist-info/WHEEL
Flask_Sendwithus-1.0.2.dist-info/metadata.json
Flask_Sendwithus-1.0.2.dist-info/pbr.json
Flask_Sendwithus-1.0.2.dist-info/top_level.txt
flask_sendwithus/__init__.py
